misbehave/__init__.py
misbehave/action.py
misbehave/common.py
misbehave/decorator.py
misbehave/selector.py
misbehave/version.py
misbehave-0.1.4.dist-info/LICENSE.txt
misbehave-0.1.4.dist-info/METADATA
misbehave-0.1.4.dist-info/WHEEL
misbehave-0.1.4.dist-info/top_level.txt
misbehave-0.1.4.dist-info/RECORD
